word2html/__init__.py
word2html/main.py
word2html-0.4.0.dist-info/METADATA
word2html-0.4.0.dist-info/WHEEL
word2html-0.4.0.dist-info/entry_points.txt
word2html-0.4.0.dist-info/licenses/LICENSE.txt
word2html-0.4.0.dist-info/RECORD
