Metadata-Version: 2.4
Name: word2html
Version: 0.4.0
Summary: A quick and dirty script to convert a Word (docx) document to html.
Project-URL: Homepage, https://github.com/bradmontgomery/word2html
Author-email: Brad Montgomery <brad@bradmontgomery.net>
License: MIT
License-File: LICENSE.txt
Keywords: html,to,word
Classifier: Development Status :: 3 - Alpha
Classifier: Intended Audience :: Developers
Classifier: License :: OSI Approved :: MIT License
Classifier: Topic :: Text Processing
Classifier: Topic :: Utilities
Requires-Python: >=3.12
Requires-Dist: pypandoc>=1.16.2
Requires-Dist: pytidylib>=0.3.2
